qrraj/__init__.py
qrraj/qr.py
qrraj/tempCodeRunnerFile.py
qrraj/__pycache__/qr.cpython-311.pyc
qrraj-0.1.5.dist-info/METADATA
qrraj-0.1.5.dist-info/WHEEL
qrraj-0.1.5.dist-info/top_level.txt
qrraj-0.1.5.dist-info/RECORD
