Metadata-Version: 2.1
Name: qrraj
Version: 0.1.5
Summary: QR CODE GENERATOR!!
Author: Aryan Raj
Requires-Dist: wheel
Requires-Dist: setuptools
Requires-Dist: qrcode
